README.md
pyproject.toml
setup.py
src/flux/__init__.py
src/flux/compressed_form_factors.py
src/flux/config.py
src/flux/debug.py
src/flux/form_factors.py
src/flux/ingersoll.py
src/flux/linalg.py
src/flux/linalg2.py
src/flux/model.py
src/flux/nmf.py
src/flux/octree.py
src/flux/plot.py
src/flux/quadtree.py
src/flux/shape.py
src/flux/solve.py
src/flux/thermal.c
src/flux/util.py
src/flux/cgal/aabb.cpp
src/flux/cgal/aabb_wrapper.cpp
src/flux/pcc/conductionQ.c
src/flux/pcc/conductionT.c
src/flux/pcc/tridag.c
src/flux/view_factor/view_factor.c
src/flux/view_factor/view_factor_narayanaswamy.c
src/fluxpy.egg-info/PKG-INFO
src/fluxpy.egg-info/SOURCES.txt
src/fluxpy.egg-info/dependency_links.txt
src/fluxpy.egg-info/top_level.txt
tests/test_compressed_form_factors.py
tests/test_form_factors.py
tests/test_shape.py
tests/test_thermal.py